softalignments/__init__.py
softalignments/functions.py
softalignments/process_alignments.py
softalignments-1.0.4.dist-info/LICENSE
softalignments-1.0.4.dist-info/METADATA
softalignments-1.0.4.dist-info/WHEEL
softalignments-1.0.4.dist-info/entry_points.txt
softalignments-1.0.4.dist-info/top_level.txt
softalignments-1.0.4.dist-info/RECORD
