Metadata-Version: 2.1
Name: softalignments
Version: 1.0.4
Summary: Neural macine translation soft alignment visualisations for web and command line
Home-page: https://github.com/M4t1ss/SoftAlignments
Author: Matīss Rikters
Author-email: m4t1ss@lielakeda.lv
License: UNKNOWN
Platform: UNKNOWN
Classifier: Programming Language :: Python :: 3
Classifier: License :: OSI Approved :: MIT License
Classifier: Operating System :: OS Independent
Requires-Python: >=3.6
